mdade/__about__.py
mdade/__init__.py
mdade/made.py
mdade/main.py
mdade/utils.py
mdade/data/__init__.py
mdade/data/module.py
mdade/data/utils.py
mdade/layers/__init__.py
mdade/layers/density_estimation.py
mdade/layers/ordered_block.py
mdade/layers/ordered_linear.py
mdade/layers/ordered_residual.py
mdade/layers/ordering_mixin.py
mdade/training/__init__.py
mdade/training/attack.py
mdade/training/callbacks.py
mdade/training/criterion.py
mdade/training/module.py
mdade/training/utils.py
mdade-0.0.5.dist-info/LICENSE
mdade-0.0.5.dist-info/METADATA
mdade-0.0.5.dist-info/WHEEL
mdade-0.0.5.dist-info/entry_points.txt
mdade-0.0.5.dist-info/top_level.txt
mdade-0.0.5.dist-info/RECORD
